fnai/__init__.py
fnai/fine_face.py
fnai/fine_hand.py
fnai/fine_weather.py
fnai-0.3.14.dist-info/METADATA
fnai-0.3.14.dist-info/WHEEL
fnai-0.3.14.dist-info/top_level.txt
fnai-0.3.14.dist-info/RECORD
